.mr.developer.cfg
MANIFEST.in
README.rst
buildout-local.cfg
buildout.cfg
setup.py
version.txt
antispoofing/__init__.py
antispoofing.lbptop.egg-info/PKG-INFO
antispoofing.lbptop.egg-info/SOURCES.txt
antispoofing.lbptop.egg-info/dependency_links.txt
antispoofing.lbptop.egg-info/entry_points.txt
antispoofing.lbptop.egg-info/requires.txt
antispoofing.lbptop.egg-info/top_level.txt
antispoofing/lbptop/__init__.py
antispoofing/lbptop/helpers/__init__.py
antispoofing/lbptop/helpers/database.py
antispoofing/lbptop/helpers/helpers.py
antispoofing/lbptop/helpers/perf_lbptop.py
antispoofing/lbptop/helpers/utils.py
antispoofing/lbptop/script/__init__.py
antispoofing/lbptop/script/lbptop_calculate_parameters.py
antispoofing/lbptop/script/lbptop_cmphistmodels.py
antispoofing/lbptop/script/lbptop_ldatrain.py
antispoofing/lbptop/script/lbptop_make_scores.py
antispoofing/lbptop/script/lbptop_mkhistmodel.py
antispoofing/lbptop/script/lbptop_result_analysis.py
antispoofing/lbptop/script/lbptop_svmtrain.py
antispoofing/lbptop/script/test.py
antispoofing/lbptop/spoof/__init__.py
antispoofing/lbptop/spoof/calclbptop.py
antispoofing/lbptop/spoof/chi2.py
antispoofing/lbptop/spoof/helpers.py
antispoofing/lbptop/spoof/scores.py