Metadata-Version: 1.1
Name: antispoofing.lbptop
Version: 2.0.3
Summary: LBP-TOP based countermeasure against facial spoofing attacks
Home-page: http://pypi.python.org/pypi/antispoofing.lbptop
Author: Tiago de Freitas Pereira
Author-email: tiagofrepereira@gmail.com
License: GPLv3
Platform: UNKNOWN
Classifier: Development Status :: 5 - Production/Stable
Classifier: Intended Audience :: Science/Research
Classifier: License :: OSI Approved :: GNU General Public License v3 (GPLv3)
Classifier: Natural Language :: English
Classifier: Programming Language :: Python
Classifier: Topic :: Scientific/Engineering :: Artificial Intelligence
